configonaut/__init__.py
configonaut/configonaut.py
configonaut-0.1.1.dist-info/LICENSE
configonaut-0.1.1.dist-info/METADATA
configonaut-0.1.1.dist-info/WHEEL
configonaut-0.1.1.dist-info/top_level.txt
configonaut-0.1.1.dist-info/RECORD
