Metadata-Version: 2.1
Name: configonaut
Version: 0.1.1
Summary: A Python library for handling JSON configuration files
Home-page: https://github.com/Antoine-ADAM/configonaut
Author: Antoine ADAM
Author-email: contact@antoineadam.fr
Classifier: Development Status :: 3 - Alpha
Classifier: Intended Audience :: Developers
Classifier: License :: OSI Approved :: MIT License
Classifier: Operating System :: OS Independent
Classifier: Programming Language :: Python :: 3
Classifier: Programming Language :: Python :: 3.6
Classifier: Programming Language :: Python :: 3.7
Classifier: Programming Language :: Python :: 3.8
Classifier: Programming Language :: Python :: 3.9
Classifier: Topic :: Software Development :: Libraries :: Python Modules
Requires-Python: >=3.6
License-File: LICENSE
